challenge_cli-0.0.1.0.dist-info/WHEEL
challenge_cli-0.0.1.0.dist-info/METADATA
challenge_cli-0.0.1.0.dist-info/entry_points.txt
challenge_cli-0.0.1.0.dist-info/DESCRIPTION.rst
challenge_cli-0.0.1.0.dist-info/RECORD
challenge_cli-0.0.1.0.dist-info/metadata.json
challenge_cli-0.0.1.0.dist-info/top_level.txt
challenges/writers.py
challenges/cli.py
challenges/utilities.py
challenges/__init__.py
challenges/local_exceptions.py
challenges/platformids.py
