Metadata-Version: 2.0
Name: challenge-cli
Version: 0.0.1.0
Summary: Programming challenges for hackers
Home-page: https://github.com/architv/chcli
Author: Archit Verma
Author-email: architv07@gmail.com
License: MIT
Keywords: programming challenges competitive topcoder codeforces tool cli
Platform: UNKNOWN
Classifier: Development Status :: 3 - Alpha
Classifier: Intended Audience :: Developers
Classifier: Topic :: Software Development :: Build Tools
Classifier: License :: OSI Approved :: MIT License
Classifier: Programming Language :: Python :: 2
Classifier: Programming Language :: Python :: 2.6
Classifier: Programming Language :: Python :: 2.7
Requires-Dist: click (>=5.0)
Requires-Dist: requests (==2.7.0)
